LICENSE
pydavsync/__init__.py
pydavsync/cli.py
pydavsync/exceptions.py
pydavsync/pull.py
pydavsync/push.py
pydavsync/sync.py
pydavsync/tools.py
pydavsync/webdav.py
pydavsync-0.1.0.dist-info/LICENSE
pydavsync-0.1.0.dist-info/WHEEL
pydavsync-0.1.0.dist-info/entry_points.txt
pydavsync-0.1.0.dist-info/METADATA
pydavsync-0.1.0.dist-info/RECORD
