Metadata-Version: 2.1
Name: pydavsync
Version: 0.1.0
Summary: Synchronization command line for WebDav.
Home-page: https://framagit.org/RomainTT/pydavsync
License: Mozilla Public License v2
Keywords: webdav,sync
Author: Romain TAPREST
Author-email: romain@taprest.fr
Requires-Python: >=3.8,<4.0
Classifier: License :: Other/Proprietary License
Classifier: Programming Language :: Python :: 3
Classifier: Programming Language :: Python :: 3.8
Classifier: Programming Language :: Python :: 3.9
Classifier: Programming Language :: Python :: 3.10
Classifier: Programming Language :: Python :: 3.11
Requires-Dist: click (>=8.1.3,<9.0.0)
Requires-Dist: webdav4 (>=0.9.7,<0.10.0)
Project-URL: Bug Tracker, https://framagit.org/RomainTT/pydavsync/-/issues
Project-URL: Repository, https://framagit.org/RomainTT/pydavsync
